MANIFEST.in
README.txt
readme.md
setup.py
mongodbforms/__init__.py
mongodbforms/documentoptions.py
mongodbforms/documents.py
mongodbforms/fieldgenerator.py
mongodbforms/fields.py
mongodbforms/util.py
mongodbforms/widgets.py
mongodbforms.egg-info/PKG-INFO
mongodbforms.egg-info/SOURCES.txt
mongodbforms.egg-info/dependency_links.txt
mongodbforms.egg-info/not-zip-safe
mongodbforms.egg-info/requires.txt
mongodbforms.egg-info/top_level.txt