Metadata-Version: 1.1
Name: mongodbforms
Version: 0.2
Summary: An implementation of django forms using mongoengine.
Home-page: http://www.schafproductions.com/projects/django-mongodb-forms/
Author: Jan Schrewe
Author-email: jan@schafproductions.com
License: New BSD License
Platform: UNKNOWN
Classifier: Development Status :: 3 - Alpha
Classifier: Environment :: Web Environment
Classifier: Intended Audience :: Developers
Classifier: License :: OSI Approved :: BSD License
Classifier: Operating System :: OS Independent
Classifier: Programming Language :: Python
Classifier: Framework :: Django
